README.rst
setup.py
pydorita/__init__.py
pydorita/pydorita.py
pydorita.egg-info/PKG-INFO
pydorita.egg-info/SOURCES.txt
pydorita.egg-info/dependency_links.txt
pydorita.egg-info/requires.txt
pydorita.egg-info/top_level.txt