Metadata-Version: 1.0
Name: pydorita
Version: 0.1
Summary: Python client for controlling a iRobot Roomba 980 (via rest980)
Home-page: https://github.com/pschmitt/pydorita
Author: Philipp Schmitt
Author-email: philipp@schmitt.co
License: GPL3
Platform: UNKNOWN
